lupin/__init__.py
lupin/errors.py
lupin/mapper.py
lupin/mapping.py
lupin/object_factories.py
lupin/processors.py
lupin/schema.py
lupin/validators_combination.py
lupin/fields/__init__.py
lupin/fields/bool.py
lupin/fields/compatibility.py
lupin/fields/constant.py
lupin/fields/date.py
lupin/fields/datetime_field.py
lupin/fields/dict.py
lupin/fields/field.py
lupin/fields/float.py
lupin/fields/int.py
lupin/fields/list.py
lupin/fields/number.py
lupin/fields/object.py
lupin/fields/polymorphic_list.py
lupin/fields/polymorphic_object.py
lupin/fields/string.py
lupin/validators/__init__.py
lupin/validators/between.py
lupin/validators/datetime_format.py
lupin/validators/dict_keys_format.py
lupin/validators/equal.py
lupin/validators/in_validator.py
lupin/validators/is_none.py
lupin/validators/length.py
lupin/validators/match.py
lupin/validators/type.py
lupin/validators/typed_dict.py
lupin/validators/url.py
lupin/validators/validator.py
lupin-2.0.0.dist-info/AUTHORS.md
lupin-2.0.0.dist-info/AUTHORS.rst
lupin-2.0.0.dist-info/LICENSE.txt
lupin-2.0.0.dist-info/METADATA
lupin-2.0.0.dist-info/WHEEL
lupin-2.0.0.dist-info/top_level.txt
lupin-2.0.0.dist-info/RECORD
